[
    {
        "id": "b5b82bfc-956e-4379-8b7e-faf84aa210a7",
        "name": "Confirm",
        "user": "user_one",
        "state": "Finished",
        "startTime": "2024-10-26T15:24:11.927839+01:00",
        "finishedTime": "2024-10-26T15:24:27.668355+01:00",
        "duration": "15 secs",
        "errorMessage": "",
        "percentageComplete": 1
    },
    {
        "id": "22cc6513-2622-4be6-a876-dbf9a52676ef",
        "name": "Save",
        "user": "user_two",
        "state": "Running",
        "startTime": "2024-10-26T15:24:40.374717+01:00",
        "finishedTime": "0001-01-01T00:00:00Z",
        "duration": "12 secs",
        "errorMessage": "",
        "percentageComplete": 0.9993924665856622
    }
]
